o7pdf/__init__.py
o7pdf/colors.py
o7pdf/pandas_basic.py
o7pdf/pandas_chart.py
o7pdf/pandas_table.py
o7pdf/report_aws_cost.py
o7pdf/report_security_hub_standard.py
o7pdf/template.py
o7pdf/res/OpenSans-Bold.ttf
o7pdf/res/OpenSans-BoldItalic.ttf
o7pdf/res/OpenSans-Italic.ttf
o7pdf/res/OpenSans-Regular.ttf
o7pdf/res/clipboard2-x-fill.svg
o7pdf/res/edit.svg
o7pdf/res/file-diff.svg
o7pdf/res/lock.svg
o7pdf/res/o7-conseils-rect.svg
o7pdf/res/question.svg
o7pdf/res/remove-emoji.svg
o7pdf/res/x-octagon.svg
o7pdf-1.2.0.dist-info/licenses/LICENSE
o7pdf-1.2.0.dist-info/METADATA
o7pdf-1.2.0.dist-info/WHEEL
o7pdf-1.2.0.dist-info/top_level.txt
o7pdf-1.2.0.dist-info/RECORD
