Metadata-Version: 2.4
Name: o7pdf
Version: 1.2.0
Summary: PDf Reports
Author-email: Philippe Gosselin <phil@o7conseils.com>
License:                                  Apache License
Keywords: python,o7conseils,pdf,report
Classifier: Development Status :: 4 - Beta
Classifier: License :: OSI Approved :: Apache Software License
Classifier: Programming Language :: Python :: 3
Classifier: Programming Language :: Python :: 3.11
Classifier: Programming Language :: Python :: 3.12
Classifier: Programming Language :: Python :: 3.13
Requires-Python: >=3.11
License-File: LICENSE
Requires-Dist: o7util[pandas]>=1.0.0
Requires-Dist: fpdf2>=2.7.9
Requires-Dist: pandas>=2.2
Requires-Dist: openpyxl>=3.1.5
Provides-Extra: dev
Requires-Dist: pytest; extra == "dev"
Requires-Dist: pytest-cov; extra == "dev"
Requires-Dist: pytest-mock; extra == "dev"
Requires-Dist: ruff; extra == "dev"
Dynamic: license-file
